{
  "dataset": "cora",
  "split_type": "fixed_splits",
  "num_seeds": 5,
  "num_splits": 1,
  "total_runs_per_model": 5,
  "d_raw": 1433,
  "d_effective": 1431,
  "rank_deficiency": true,
  "orthonormality_error": 1.10451633394959e-08,
  "epochs": 200,
  "hidden_dim": 256,
  "batch_size": 140,
  "learning_rate": 0.01,
  "weight_decay": 0.0005,
  "models": {
    "standard_X_scaled": {
      "name": "(a) Standard MLP on X (scaled)",
      "test_accuracy": {
        "mean": 0.5164000153541565,
        "std": 0.001356469624450057,
        "min": 0.5139999985694885,
        "max": 0.5180000066757202
      },
      "convergence_metrics": {
        "speed_to_90": {
          "mean": 1.6,
          "std": 0.4898979485566356
        },
        "speed_to_95": {
          "mean": 51.8,
          "std": 28.91643131508451
        },
        "speed_to_99": {
          "mean": 75.4,
          "std": 37.06534769835567
        },
        "auc": {
          "mean": 0.9635695463401784,
          "std": 0.02555725005502976
        },
        "convergence_rate": {
          "mean": 0.0028000003099441528,
          "std": 0.001122497393386565
        },
        "final_acc": {
          "mean": 0.5128000259399415,
          "std": 0.002039600249441497
        }
      },
      "checkpoint_accuracies": {
        "10": {
          "mean": 0.45280001759529115,
          "std": 0.03534063381876791
        },
        "20": {
          "mean": 0.4616000235080719,
          "std": 0.03697350976454432
        },
        "40": {
          "mean": 0.47760003209114077,
          "std": 0.033714094070129055
        },
        "80": {
          "mean": 0.4928000271320343,
          "std": 0.011070687424402847
        },
        "160": {
          "mean": 0.5132000088691712,
          "std": 0.0009797832826298088
        },
        "200": {
          "mean": 0.5128000259399415,
          "std": 0.002039600249441497
        }
      }
    },
    "standard_V_scaled": {
      "name": "(b) Standard MLP on V (scaled)",
      "test_accuracy": {
        "mean": 0.315200012922287,
        "std": 0.0047074352641292075,
        "min": 0.3060000240802765,
        "max": 0.3190000057220459
      },
      "convergence_metrics": {
        "speed_to_90": {
          "mean": 64.6,
          "std": 6.468384651518491
        },
        "speed_to_95": {
          "mean": 67.2,
          "std": 5.67097875150313
        },
        "speed_to_99": {
          "mean": 69.4,
          "std": 5.314132102234569
        },
        "auc": {
          "mean": 0.9226805559141246,
          "std": 0.032629511452793934
        },
        "convergence_rate": {
          "mean": 0.001860000193119049,
          "std": 0.0015538340135971343
        },
        "final_acc": {
          "mean": 0.267600005865097,
          "std": 0.0023323854846428235
        }
      },
      "checkpoint_accuracies": {
        "10": {
          "mean": 0.1576000064611435,
          "std": 0.018736060643914927
        },
        "20": {
          "mean": 0.15400001108646394,
          "std": 0.01802220932604277
        },
        "40": {
          "mean": 0.1732000082731247,
          "std": 0.017735840413454662
        },
        "80": {
          "mean": 0.3088000178337097,
          "std": 0.01857310681251563
        },
        "160": {
          "mean": 0.2732000112533569,
          "std": 0.004833217331823263
        },
        "200": {
          "mean": 0.267600005865097,
          "std": 0.0023323854846428235
        }
      }
    },
    "rownorm_V": {
      "name": "(c) RowNorm MLP on V (unscaled)",
      "test_accuracy": {
        "mean": 0.18760001063346862,
        "std": 0.01564097464827093,
        "min": 0.16500000655651093,
        "max": 0.20500001311302185
      },
      "convergence_metrics": {
        "speed_to_90": {
          "mean": 4.2,
          "std": 8.399999999999999
        },
        "speed_to_95": {
          "mean": 4.8,
          "std": 9.108238029388561
        },
        "speed_to_99": {
          "mean": 5.0,
          "std": 9.50789145920377
        },
        "auc": {
          "mean": 1.138436506009874,
          "std": 0.14320791951578968
        },
        "convergence_rate": {
          "mean": 0.0012000000476837158,
          "std": 0.0012992307085965386
        },
        "final_acc": {
          "mean": 0.17200000882148742,
          "std": 0.025424397444360383
        }
      },
      "checkpoint_accuracies": {
        "10": {
          "mean": 0.18320000767707825,
          "std": 0.0051536386006071
        },
        "20": {
          "mean": 0.19600000977516174,
          "std": 0.007899364962588166
        },
        "40": {
          "mean": 0.3168000102043152,
          "std": 0.014998675066610045
        },
        "80": {
          "mean": 0.21640000641345977,
          "std": 0.026635315621584433
        },
        "160": {
          "mean": 0.15880000591278076,
          "std": 0.011356057357205103
        },
        "200": {
          "mean": 0.17200000882148742,
          "std": 0.025424397444360383
        }
      }
    }
  }
}